server/__init__.py
server/server.py
server/common/__init__.py
server/common/descriptrs.py
server/common/errors.py
server/common/metaclasses.py
server/common/utils.py
server/common/variables.py
server/doc/__init__.py
server/doc/source/__init__.py
server/doc/source/conf.py
server/logs/__init__.py
server/logs/client_log_config.py
server/logs/decor.py
server/logs/server_log_config.py
server/serverapp/__init__.py
server/serverapp/database_server.py
server/serverapp/server_gui.py
server/unit_tests/__init__.py
server/unit_tests/test_client.py
server/unit_tests/test_server.py
messenger_123_server-0.0.3.dist-info/METADATA
messenger_123_server-0.0.3.dist-info/WHEEL
messenger_123_server-0.0.3.dist-info/top_level.txt
messenger_123_server-0.0.3.dist-info/RECORD
