Metadata-Version: 2.1
Name: messenger-123-server
Version: 0.0.3
Summary: messenger_123_server
Home-page: UNKNOWN
Author: Semushkin Anton
Author-email: rkzton@yandex.ru
License: UNKNOWN
Platform: UNKNOWN
Requires-Dist: PyQt5
Requires-Dist: sqlalchemy
Requires-Dist: pycryptodome
Requires-Dist: pycryptodomex
